flow_helpers_tps/__init__.py
flow_helpers_tps/_bingwmt.py
flow_helpers_tps/_covidtracking.py
flow_helpers_tps/_dcm.py
flow_helpers_tps/_facebook.py
flow_helpers_tps/_file.py
flow_helpers_tps/_firebasetransform.py
flow_helpers_tps/_funneltransform.py
flow_helpers_tps/_gatransform.py
flow_helpers_tps/_gbq.py
flow_helpers_tps/_gcs.py
flow_helpers_tps/_gdrive.py
flow_helpers_tps/_googleanalytics.py
flow_helpers_tps/_gsc.py
flow_helpers_tps/_gsheet.py
flow_helpers_tps/_impact.py
flow_helpers_tps/_journera.py
flow_helpers_tps/_listen360.py
flow_helpers_tps/_mssql.py
flow_helpers_tps/_s3.py
flow_helpers_tps/_sa360.py
flow_helpers_tps/_salesforce.py
flow_helpers_tps/_scrapinghub.py
flow_helpers_tps/_sftp.py
flow_helpers_tps/_sharepoint.py
flow_helpers_tps/_snowflake.py
flow_helpers_tps/_time.py
flow_helpers_tps-2023.5.31.1939.dist-info/LICENSE
flow_helpers_tps-2023.5.31.1939.dist-info/METADATA
flow_helpers_tps-2023.5.31.1939.dist-info/WHEEL
flow_helpers_tps-2023.5.31.1939.dist-info/RECORD
