Metadata-Version: 2.1
Name: flow-helpers-tps
Version: 2023.5.31.1939
Summary: Handy helpers for ETL and API interfacing.
License: MIT
Author: joshliu3
Author-email: jliu@theparkingspot.com
Requires-Python: >=3.10,<4.0
Classifier: License :: OSI Approved :: MIT License
Classifier: Programming Language :: Python :: 3
Classifier: Programming Language :: Python :: 3.10
Classifier: Programming Language :: Python :: 3.11
Requires-Dist: Office365-REST-Python-Client (==2.3.3)
Requires-Dist: SQLAlchemy (>=2.0.9,<3.0.0)
Requires-Dist: boto3 (>=1.26.110,<2.0.0)
Requires-Dist: facebook-business (>=16.0.2,<17.0.0)
Requires-Dist: flatdict (==4.0.0)
Requires-Dist: google (>=3.0.0,<4.0.0)
Requires-Dist: google-api-python-client (>=2.85.0,<3.0.0)
Requires-Dist: pandas (>=2.0.0,<3.0.0)
Requires-Dist: pendulum (>=2.1.2,<3.0.0)
Requires-Dist: pysftp (==0.2.9)
Requires-Dist: toml (==0.10.2)
